tomfig/__init__.py
tomfig/main.py
tomfig-0.1.0.dist-info/LICENSE.md
tomfig-0.1.0.dist-info/METADATA
tomfig-0.1.0.dist-info/WHEEL
tomfig-0.1.0.dist-info/RECORD
