Metadata-Version: 2.1
Name: tomfig
Version: 0.1.0
Summary: 
Author: Anthony Mugendi
Author-email: ngurumugz@gmail.com
Requires-Python: >=3.8,<4.0
Classifier: Programming Language :: Python :: 3
Classifier: Programming Language :: Python :: 3.8
Classifier: Programming Language :: Python :: 3.9
Classifier: Programming Language :: Python :: 3.10
Classifier: Programming Language :: Python :: 3.11
Requires-Dist: tomli (>=2.0.1,<3.0.0)
